qiskit_addon_slc/__init__.py
qiskit_addon_slc/bounds/__init__.py
qiskit_addon_slc/bounds/backward.py
qiskit_addon_slc/bounds/commutator_bounds.py
qiskit_addon_slc/bounds/forward.py
qiskit_addon_slc/bounds/light_cone.py
qiskit_addon_slc/bounds/local_scales.py
qiskit_addon_slc/bounds/merge.py
qiskit_addon_slc/bounds/speed_limit.py
qiskit_addon_slc/bounds/trivial.py
qiskit_addon_slc/utils/__init__.py
qiskit_addon_slc/utils/annotations.py
qiskit_addon_slc/utils/boxes.py
qiskit_addon_slc/utils/circuit_iter.py
qiskit_addon_slc/utils/davidson.py
qiskit_addon_slc/utils/find_indices.py
qiskit_addon_slc/utils/noise_model_paulis.py
qiskit_addon_slc/utils/remove_measure.py
qiskit_addon_slc/visualization/__init__.py
qiskit_addon_slc/visualization/accumulate_filtered_bounds.py
qiskit_addon_slc/visualization/overlay_bounds.py
qiskit_addon_slc/visualization/render_bounds.py
qiskit_addon_slc-0.1.0.dist-info/METADATA
qiskit_addon_slc-0.1.0.dist-info/WHEEL
qiskit_addon_slc-0.1.0.dist-info/licenses/LICENSE.txt
qiskit_addon_slc-0.1.0.dist-info/RECORD
